dynamodb/__init__.py
dynamodb/errorHandle.py
dynamodb/repository.py
dynamodb/utils.py
MentheDb-0.0.4.dist-info/LICENSE
MentheDb-0.0.4.dist-info/METADATA
MentheDb-0.0.4.dist-info/WHEEL
MentheDb-0.0.4.dist-info/top_level.txt
MentheDb-0.0.4.dist-info/RECORD
