Metadata-Version: 2.1
Name: MentheDb
Version: 0.0.4
Summary: A package with dynamodb functionalities
Home-page: https://github.com/ProjectIbX/Menthedb
Author: Menthe Authors
Author-email: nikolay.gyuneliev@gmail.com
License: UNKNOWN
Project-URL: Bug Tracker, https://github.com/ProjectIbX/Menthedb/src
Platform: UNKNOWN
Classifier: Programming Language :: Python :: 3
Classifier: License :: OSI Approved :: MIT License
Classifier: Operating System :: OS Independent
Requires-Python: >=3.8
License-File: LICENSE
